sshspawner/__init__.py
sshspawner/sshspawner.py
sshspawner-0.0.1a5.dist-info/LICENSE
sshspawner-0.0.1a5.dist-info/METADATA
sshspawner-0.0.1a5.dist-info/WHEEL
sshspawner-0.0.1a5.dist-info/top_level.txt
sshspawner-0.0.1a5.dist-info/RECORD
