Metadata-Version: 2.1
Name: sshspawner
Version: 0.0.1a5
Summary: SSH Spawner: A custom spawner for Jupyterhub to spawn                    notebooks over SSH
Home-page: https://github.com/rasmunk/sshspawner.git
Author: Rasmus Munk
Author-email: munk1@live.dk
License: BSD
Keywords: Interactive,Interpreter,Shell,Web,JupyterHub,Spawner
Platform: Linux
Platform: Mac OS X
Classifier: Intended Audience :: Developers
Classifier: Intended Audience :: System Administrators
Classifier: Intended Audience :: Science/Research
Classifier: License :: OSI Approved :: BSD License
Classifier: Programming Language :: Python :: 3.6
Classifier: Programming Language :: Python :: 3.7
Classifier: Programming Language :: Python :: 3.8
Classifier: Programming Language :: Python :: 3.9
Requires-Dist: cryptography (==3.2.1)
Requires-Dist: asyncssh
Requires-Dist: traitlets (==4.3.3)
Requires-Dist: jupyterhub
Provides-Extra: dev
Requires-Dist: flake8 (==3.8.4) ; extra == 'dev'
Requires-Dist: black (==20.8b1) ; extra == 'dev'
Requires-Dist: docutils (==0.16) ; extra == 'dev'
Provides-Extra: test
Requires-Dist: pytest ; extra == 'test'
